beintelli_platform_python_sdk/__init__.py
beintelli_platform_python_sdk/measurement_list.py
beintelli_platform_python_sdk/user.py
beintelli_platform_python_sdk/apis/__init__.py
beintelli_platform_python_sdk/apis/config.py
beintelli_platform_python_sdk/apis/data_api.py
beintelli_platform_python_sdk/apis/login_api.py
beintelli_platform_python_sdk/apis/measurement_api.py
beintelli_platform_python_sdk/apis/service_api.py
beintelli_platform_python_sdk/utils/__init__.py
beintelli_platform_python_sdk/utils/access.py
beintelli_platform_python_sdk/utils/types.py
beintelli_platform_python_sdk-0.1.4.dist-info/LICENSE
beintelli_platform_python_sdk-0.1.4.dist-info/METADATA
beintelli_platform_python_sdk-0.1.4.dist-info/WHEEL
beintelli_platform_python_sdk-0.1.4.dist-info/top_level.txt
beintelli_platform_python_sdk-0.1.4.dist-info/RECORD
