Metadata-Version: 2.1
Name: beintelli-platform-python-sdk
Version: 0.1.4
Summary: A software development kit for the integration of the Beintelli API
Author-email: Elias Inguanta <inguanta@campus.tu-berlin.de>
Project-URL: Homepage, https://api.dev.be-intelli.com/platform/#/
Project-URL: Repository, https://git.tu-berlin.de/beintelli-plattform-sdk/beintelli-platform-python-sdk.git
Requires-Python: >=3.8
License-File: LICENSE
Requires-Dist: requests ~=2.31.0
